Workbook

Sheet Data 
M18: All the following data have been extracted from the consolidated balance sheet of Infosys Ltd for the years 2019-2024 from their published annual reports
M22: https://www.infosys.com/investors/reports-filings/annual-report/annual-reports.html

Sheet Income Statement
D6: Income Statement For the year ending 31st march
H7: 2019-20 | I7: 2020-21 | J7: 2021-22 | K7: 2022-23 | L7: 2023-24
D8: Particulars | H8: Amount | I8: Amount | J8: Amount | K8: Amount | L8: Amount
D9: Revenue From Operations | H9: 90791 | I9: 100472 | J9: 121641 | K9: 146767 | L9: 153670
D10: Other Income | H10: 2803 | I10: 2201 | J10: 2295 | K10: 2701 | L10: 4711
D11: Total Income | H11: =H9+H10 -> 93594 | I11: =I9+I10 -> 102673 | J11: =J9+J10 -> 123936 | K11: =K9+K10 -> 149468 | L11: =L9+L10 -> 158381
D12: Total Expenses | H12: 71587 | I12: 76045 | J12: 93826 | K12: 116146 | L12: 122393
D13: Profit Before Tax | H13: =H11-H12 -> 22007 | I13: =I11-I12 -> 26628 | J13: =J11-J12 -> 30110 | K13: =K11-K12 -> 33322 | L13: =L11-L12 -> 35988
D14: Tax Expense | H14: 5368 | I14: 7205 | J14: 7964 | K14: 9214 | L14: 9740
D15: Profit After Tax | H15: =H13-H14 -> 16639 | I15: =I13-I14 -> 19423 | J15: =J13-J14 -> 22146 | K15: =K13-K14 -> 24108 | L15: =L13-L14 -> 26248
D18: Revenue Growth % | I18: =(I9-H9)/H9 -> 0.10662951 | J18: =(J9-I9)/I9 -> 0.21069552 | K18: =(K9-J9)/J9 -> 0.20655864 | L18: =(L9-K9)/K9 -> 0.047033734
D19: Expense Growth % | I19: =(I12-H12)/H12 -> 0.062273877 | J19: =(J12-I12)/I12 -> 0.23382208 | K19: =(K12-J12)/J12 -> 0.23788715 | L19: =(L12-K12)/K12 -> 0.053785752
D20: PAT Growth % | I20: =(I15-H15)/H15 -> 0.16731775 | J20: =(J15-I15)/I15 -> 0.14019461 | K20: =(K15-J15)/J15 -> 0.088593877 | L20: =(L15-K15)/K15 -> 0.088767214
D21: Net Profit Margin % | H21: =H15/H9 -> 0.18326706 | I21: =I15/I9 -> 0.19331754 | J21: =J15/J9 -> 0.18206033 | K21: =K15/K9 -> 0.16426036 | L21: =L15/L9 -> 0.17080757
D22: Effective Tax Rate % | H22: =H14/H13 -> 0.24392239 | I22: =I14/I13 -> 0.27057984 | J22: =J14/J13 -> 0.26449684 | K22: =K14/K13 -> 0.27651401 | L22: =L14/L13 -> 0.27064577

Sheet Balance Sheet
D4: Financial Position For The Year Ending 31st March
D6: Particulars | E6: 2019-20 | F6: 2020-21 | G6: 2021-22 | H6: 2022-23 | I6: 2023-24
D7: Assets
D8: Current Assets
D9: Total Current Assets | E9: 54576 | F9: 60733 | G9: 67185 | H9: 70881 | I9: 89432
D10: Non-current Assets
D11: Total Non-current Assets | E11: 38192 | F11: 47653 | G11: 50700 | H11: 54935 | I11: 48382
D12: Total Assets | E12: =E9+E11 -> 92768 | F12: =F9+F11 -> 108386 | G12: =G9+G11 -> 117885 | H12: =H9+H11 -> 125816 | I12: =I9+I11 -> 137814
D13: Equity
D14: Total Equity | E14: 65844 | F14: 76782 | G14: 75736 | H14: 75795 | I14: 88461
D15: Liabilities
D16: Total Current Liabilities | E16: 20856 | F16: 23865 | G16: 33603 | H16: 39186 | I16: 38794
D17: Total Non-current Liabilities | E17: 6068 | F17: 7739 | G17: 8546 | H17: 10835 | I17: 10559
D18: Total Liabilities | E18: =E16+E17 -> 26924 | F18: =F16+F17 -> 31604 | G18: =G16+G17 -> 42149 | H18: =H16+H17 -> 50021 | I18: =I16+I17 -> 49353
D19: Total Equity and Liabilities | E19: =E14+E18 -> 92768 | F19: =F14+F18 -> 108386 | G19: =G14+G18 -> 117885 | H19: =H14+H18 -> 125816 | I19: =I14+I18 -> 137814

Sheet Cash Flow
D6: Particulars | E6: 2019-20 | F6: 2020-21 | G6: 2021-22 | H6: 2022-23 | I6: 2023-24
D7: Net Cash from Operating Activities | E7: 17003 | F7: 23224 | G7: 23885 | H7: 22467 | I7: 25210
D8: Net Cash from Investing Activities | E8: -239 | F8: -7456 | G8: -6416 | H8: -1209 | I8: -5009
D9: Net Cash from Financing Activities | E9: -17591 | F9: -9786 | G9: -24642 | H9: -26695 | I9: -17504
D10: Net Increase / (Decrease) in Cash | E10: =E7+E8+E9 -> -827 | F10: =F7+F8+F9 -> 5982 | G10: =G7+G8+G9 -> -7173 | H10: =H7+H8+H9 -> -5437 | I10: =I7+I8+I9 -> 2697
D11: Cash & Cash Equivalents at Beginning | E11: 19476 | F11: 18732 | G11: 24645 | H11: 17610 | I11: 12089
D12: Cash & Cash Equivalents at End | E12: =E10+E11 -> 18649 | F12: =F10+F11 -> 24714 | G12: =G10+G11 -> 17472 | H12: =H10+H11 -> 12173 | I12: =I10+I11 -> 14786

Sheet Ratios
D6: Particulars | E6: 2019-20 | F6: 2020-21 | G6: 2021-22 | H6: 2022-23 | I6: 2023-24
D7: Revenue Growth % | F7: =('Income Statement'!I9-'Income Statement'!H9)/'Income Statement'!H9 -> 0.10662951 | G7: =('Income Statement'!J9-'Income Statement'!I9)/'Income Statement'!I9 -> 0.21069552 | H7: =('Income Statement'!K9-'Income Statement'!J9)/'Income Statement'!J9 -> 0.20655864 | I7: =('Income Statement'!L9-'Income Statement'!K9)/'Income Statement'!K9 -> 0.047033734
D8: Profit Growth % | F8: =('Income Statement'!I15-'Income Statement'!H15)/'Income Statement'!H15 -> 0.16731775 | G8: =('Income Statement'!J15-'Income Statement'!I15)/'Income Statement'!I15 -> 0.14019461 | H8: =('Income Statement'!K15-'Income Statement'!J15)/'Income Statement'!J15 -> 0.088593877 | I8: =('Income Statement'!L15-'Income Statement'!K15)/'Income Statement'!K15 -> 0.088767214
D9: Net Profit Margin % | E9: ='Income Statement'!H15/Table5[[#This Row],[Column5]] -> 0.18326706 | F9: ='Income Statement'!I15/Table5[[#This Row],[Column6]] -> 0.19331754 | G9: ='Income Statement'!J15/Table5[[#This Row],[Column7]] -> 0.18206033 | H9: ='Income Statement'!K15/Table5[[#This Row],[Column8]] -> 0.16426036 | I9: ='Income Statement'!L15/Table5[[#This Row],[Column9]] -> 0.17080757
D10: ROA % | E10: ='Income Statement'!H15/'Balance Sheet'!E12 -> 0.17936142 | F10: ='Income Statement'!I15/'Balance Sheet'!F12 -> 0.17920211 | G10: ='Income Statement'!J15/'Balance Sheet'!G12 -> 0.18786105 | H10: ='Income Statement'!K15/'Balance Sheet'!H12 -> 0.19161315 | I10: ='Income Statement'!L15/'Balance Sheet'!I12 -> 0.1904596
D11: ROE % | E11: ='Income Statement'!H15/'Balance Sheet'!E14 -> 0.25270336 | F11: ='Income Statement'!I15/'Balance Sheet'!F14 -> 0.25296293 | G11: ='Income Statement'!J15/'Balance Sheet'!G14 -> 0.29241048 | H11: ='Income Statement'!K15/'Balance Sheet'!H14 -> 0.31806847 | I11: ='Income Statement'!L15/'Balance Sheet'!I14 -> 0.29671833
D12: Current Ratio | E12: ='Balance Sheet'!E9/'Balance Sheet'!E16 -> 2.6168009 | F12: ='Balance Sheet'!F9/'Balance Sheet'!F16 -> 2.5448565 | G12: ='Balance Sheet'!G9/'Balance Sheet'!G16 -> 1.9993751 | H12: ='Balance Sheet'!H9/'Balance Sheet'!H16 -> 1.8088348 | I12: ='Balance Sheet'!I9/'Balance Sheet'!I16 -> 2.3053049
D13: Debt Ratio | E13: ='Balance Sheet'!E18/'Balance Sheet'!E12 -> 0.29022939 | F13: ='Balance Sheet'!F18/'Balance Sheet'!F12 -> 0.29158747 | G13: ='Balance Sheet'!G18/'Balance Sheet'!G12 -> 0.35754337 | H13: ='Balance Sheet'!H18/'Balance Sheet'!H12 -> 0.39757265 | I13: ='Balance Sheet'!I18/'Balance Sheet'!I12 -> 0.35811311
D14: Debt to Equity | E14: ='Balance Sheet'!E18/Table1[[#This Row],[2019-20]] -> 0.4089059 | F14: ='Balance Sheet'!F18/Table1[[#This Row],[2020-21]] -> 0.41160689 | G14: ='Balance Sheet'!G18/Table1[[#This Row],[2021-22]] -> 0.5565253 | H14: ='Balance Sheet'!H18/Table1[[#This Row],[2022-23]] -> 0.65995118 | I14: ='Balance Sheet'!I18/Table1[[#This Row],[2023-24]] -> 0.55790687
D15: Asset Turnover | E15: ='Income Statement'!H9/'Balance Sheet'!E12 -> 0.97868877 | F15: ='Income Statement'!I9/'Balance Sheet'!F12 -> 0.92698319 | G15: ='Income Statement'!J9/'Balance Sheet'!G12 -> 1.0318616 | H15: ='Income Statement'!K9/'Balance Sheet'!H12 -> 1.166521 | I15: ='Income Statement'!L9/'Balance Sheet'!I12 -> 1.1150536
D16: Operating Cash Flow Ratio | E16: ='Cash Flow'!E7/Table1[[#This Row],[2019-20]] -> 0.815257 | F16: ='Cash Flow'!F7/Table1[[#This Row],[2020-21]] -> 0.97314058 | G16: ='Cash Flow'!G7/Table1[[#This Row],[2021-22]] -> 0.71079963 | H16: ='Cash Flow'!H7/Table1[[#This Row],[2022-23]] -> 0.57334252 | I16: ='Cash Flow'!I7/Table1[[#This Row],[2023-24]] -> 0.64984276

Sheet Dashboard
M4: INFOSYS FINANCIAL DASHBOARD(2024)
M7: Revenue | N7: PAT | O7: Total Assets | P7: Operating Cash Flow | Q7: ROE | R7: Current Ratio | S7: Debt to Equity | T7: Net Profit Margin
M8: 153670 | N8: 26248 | O8: 137814 | P8: 25210 | Q8: 0.29671833 | R8: 2.3053049 | S8: 0.55790687 | T8: 0.17080757
AG14: .
